{
    "season": "set3.5",
    "traits": [
        {
            "key": "Astro",
            "ingameKey": "Astro",
            "name": "Astro",
            "desc": "",
            "imageUrl": "//cdn.lolchess.gg/images/tft/traiticons-darken/trait_icon_astro.png",
            "blackImageUrl": "//cdn.lolchess.gg/images/tft/traiticons-black/trait_icon_astro.png",
            "whiteImageUrl": "//cdn.lolchess.gg/images/tft/traiticons-white/trait_icon_astro.png",
            "type": "ORIGIN",
            "styles": [
                {
                    "style": "gold",
                    "min": 3
                }
            ],
            "stats": {
                "3": "Astro Champions reduce their mana costs by 30"
            }
        },
        {
            "key": "Battlecast",
            "ingameKey": "Battlecast",
            "name": "Battlecast",
            "desc": "Battlecast champions, upon dealing or taking 10 instances of damage, heal if below half health, or deal magic damage to the nearest enemy if above half.",
            "imageUrl": "//cdn.lolchess.gg/images/tft/traiticons-darken/trait_icon_battlecast.png",
            "blackImageUrl": "//cdn.lolchess.gg/images/tft/traiticons-black/trait_icon_battlecast.png",
            "whiteImageUrl": "//cdn.lolchess.gg/images/tft/traiticons-white/trait_icon_battlecast.png",
            "type": "ORIGIN",
            "styles": [
                {
                    "style": "bronze",
                    "min": 2,
                    "max": 3
                },
                {
                    "style": "silver",
                    "min": 4,
                    "max": 5
                },
                {
                    "style": "gold",
                    "min": 6,
                    "max": 7
                },
                {
                    "style": "chromatic",
                    "min": 8
                }
            ],
            "stats": {
                "2": "80 Healing or Damage",
                "4": "180 Healing or Damage",
                "6": "480 Healing or Damage",
                "8": "1000 Healing or Damage"
            }
        },
        {
            "key": "Blademaster",
            "ingameKey": "Set3_Blademaster",
            "name": "Blademaster",
            "desc": "Blademasters' Basic Attacks have a chance to trigger two additional attacks against their target. These additional attacks deal damage like Basic Attacks and trigger on-hit effects.",
            "imageUrl": "//cdn.lolchess.gg/images/tft/traiticons-darken/trait_icon_blademaster.png",
            "blackImageUrl": "//cdn.lolchess.gg/images/tft/traiticons-black/trait_icon_blademaster.png",
            "whiteImageUrl": "//cdn.lolchess.gg/images/tft/traiticons-white/trait_icon_blademaster.png",
            "type": "CLASS",
            "styles": [
                {
                    "style": "bronze",
                    "min": 3,
                    "max": 5
                },
                {
                    "style": "silver",
                    "min": 6,
                    "max": 8
                },
                {
                    "style": "gold",
                    "min": 9
                }
            ],
            "stats": {
                "3": "30% Chance to trigger",
                "6": "65% Chance to trigger",
                "9": "100% Chance to trigger"
            }
        },
        {
            "key": "Blaster",
            "ingameKey": "Set3_Blaster",
            "name": "Blaster",
            "desc": "Every fourth Basic Attack from a Blaster fires additional attacks at random enemies. These additional attacks deal damage like Basic Attacks, trigger on-hit effects and can critically hit.",
            "imageUrl": "//cdn.lolchess.gg/images/tft/traiticons-darken/trait_icon_blaster.png",
            "blackImageUrl": "//cdn.lolchess.gg/images/tft/traiticons-black/trait_icon_blaster.png",
            "whiteImageUrl": "//cdn.lolchess.gg/images/tft/traiticons-white/trait_icon_blaster.png",
            "type": "CLASS",
            "styles": [
                {
                    "style": "bronze",
                    "min": 2,
                    "max": 3
                },
                {
                    "style": "gold",
                    "min": 4
                }
            ],
            "stats": {
                "2": "3 Additional Attacks",
                "4": "6 Additional Attacks"
            }
        },
        {
            "key": "Brawler",
            "ingameKey": "Set3_Brawler",
            "name": "Brawler",
            "desc": "Brawlers gain bonus Maximum Health.",
            "imageUrl": "//cdn.lolchess.gg/images/tft/traiticons-darken/trait_icon_brawler.png",
            "blackImageUrl": "//cdn.lolchess.gg/images/tft/traiticons-black/trait_icon_brawler.png",
            "whiteImageUrl": "//cdn.lolchess.gg/images/tft/traiticons-white/trait_icon_brawler.png",
            "type": "CLASS",
            "styles": [
                {
                    "style": "bronze",
                    "min": 2,
                    "max": 3
                },
                {
                    "style": "gold",
                    "min": 4
                }
            ],
            "stats": {
                "2": "350 Bonus Health",
                "4": "600 Bonus Health"
            }
        },
        {
            "key": "Celestial",
            "ingameKey": "Set3_Celestial",
            "name": "Celestial",
            "desc": "All allies heal for some of the damage they deal with spells and attacks.",
            "imageUrl": "//cdn.lolchess.gg/images/tft/traiticons-darken/trait_icon_celestial.png",
            "blackImageUrl": "//cdn.lolchess.gg/images/tft/traiticons-black/trait_icon_celestial.png",
            "whiteImageUrl": "//cdn.lolchess.gg/images/tft/traiticons-white/trait_icon_celestial.png",
            "type": "ORIGIN",
            "styles": [
                {
                    "style": "bronze",
                    "min": 2,
                    "max": 3
                },
                {
                    "style": "silver",
                    "min": 4,
                    "max": 5
                },
                {
                    "style": "gold",
                    "min": 6
                }
            ],
            "stats": {
                "2": "15% Healing",
                "4": "45% Healing",
                "6": "150% Healing"
            }
        },
        {
            "key": "Chrono",
            "ingameKey": "Chrono",
            "name": "Chrono",
            "desc": "All allies gain 15% Attack Speed every some seconds.",
            "imageUrl": "//cdn.lolchess.gg/images/tft/traiticons-darken/trait_icon_chrono.png",
            "blackImageUrl": "//cdn.lolchess.gg/images/tft/traiticons-black/trait_icon_chrono.png",
            "whiteImageUrl": "//cdn.lolchess.gg/images/tft/traiticons-white/trait_icon_chrono.png",
            "type": "ORIGIN",
            "styles": [
                {
                    "style": "bronze",
                    "min": 2,
                    "max": 3
                },
                {
                    "style": "silver",
                    "min": 4,
                    "max": 5
                },
                {
                    "style": "gold",
                    "min": 6,
                    "max": 7
                },
                {
                    "style": "chromatic",
                    "min": 8
                }
            ],
            "stats": {
                "2": "every 8 seconds",
                "4": "every 3 seconds",
                "6": "every 1 seconds",
                "8": "every 0.5 seconds"
            }
        },
        {
            "key": "Cybernetic",
            "ingameKey": "Cybernetic",
            "name": "Cybernetic",
            "desc": "Cybernetic champions with at least one item gain Health and Attack Damage.",
            "imageUrl": "//cdn.lolchess.gg/images/tft/traiticons-darken/trait_icon_cybernetic.png",
            "blackImageUrl": "//cdn.lolchess.gg/images/tft/traiticons-black/trait_icon_cybernetic.png",
            "whiteImageUrl": "//cdn.lolchess.gg/images/tft/traiticons-white/trait_icon_cybernetic.png",
            "type": "ORIGIN",
            "styles": [
                {
                    "style": "bronze",
                    "min": 3,
                    "max": 5
                },
                {
                    "style": "gold",
                    "min": 6
                }
            ],
            "stats": {
                "3": "300 Health and 35 Attack Damage",
                "6": "550 Health and 70 Attack Damage"
            }
        },
        {
            "key": "DarkStar",
            "ingameKey": "DarkStar",
            "name": "Dark Star",
            "desc": "When any ally champion dies, all other allied Dark Star Champions gain Attack Damage and Spell Power",
            "imageUrl": "//cdn.lolchess.gg/images/tft/traiticons-darken/trait_icon_darkstar.png",
            "blackImageUrl": "//cdn.lolchess.gg/images/tft/traiticons-black/trait_icon_darkstar.png",
            "whiteImageUrl": "//cdn.lolchess.gg/images/tft/traiticons-white/trait_icon_darkstar.png",
            "type": "ORIGIN",
            "styles": [
                {
                    "style": "bronze",
                    "min": 2,
                    "max": 3
                },
                {
                    "style": "silver",
                    "min": 4,
                    "max": 5
                },
                {
                    "style": "gold",
                    "min": 6,
                    "max": 7
                },
                {
                    "style": "chromatic",
                    "min": 8
                }
            ],
            "stats": {
                "2": "Attack Damage and Spell Power +8",
                "4": "Attack Damage and Spell Power +18",
                "6": "Attack Damage and Spell Power +28",
                "8": "Attack Damage and Spell Power +48"
            }
        },
        {
            "key": "Demolitionist",
            "ingameKey": "Demolitionist",
            "name": "Demolitionist",
            "desc": "",
            "imageUrl": "//cdn.lolchess.gg/images/tft/traiticons-darken/trait_icon_demolitionist.png",
            "blackImageUrl": "//cdn.lolchess.gg/images/tft/traiticons-black/trait_icon_demolitionist.png",
            "whiteImageUrl": "//cdn.lolchess.gg/images/tft/traiticons-white/trait_icon_demolitionist.png",
            "type": "CLASS",
            "styles": [
                {
                    "style": "gold",
                    "min": 2
                }
            ],
            "stats": {
                "2": "Damage from Demolitionists' spellcasts stun their for 1.50 seconds. (Once per spellcast)"
            }
        },
        {
            "key": "Infiltrator",
            "ingameKey": "Infiltrator",
            "name": "Infiltrator",
            "desc": "Innate: At the start of combat, Infiltrators move to the enemy's backline. Infiltrators gain Attack Speed for 6 seconds at the start of combat, refreshes on takedown",
            "imageUrl": "//cdn.lolchess.gg/images/tft/traiticons-darken/trait_icon_infiltrator.png",
            "blackImageUrl": "//cdn.lolchess.gg/images/tft/traiticons-black/trait_icon_infiltrator.png",
            "whiteImageUrl": "//cdn.lolchess.gg/images/tft/traiticons-white/trait_icon_infiltrator.png",
            "type": "CLASS",
            "styles": [
                {
                    "style": "bronze",
                    "min": 2,
                    "max": 3
                },
                {
                    "style": "silver",
                    "min": 4,
                    "max": 5
                },
                {
                    "style": "gold",
                    "min": 6
                }
            ],
            "stats": {
                "2": "40% Bonus Attack Speed",
                "4": "80% Bonus Attack Speed",
                "6": "150% Bonus Attack Speed"
            }
        },
        {
            "key": "ManaReaver",
            "ingameKey": "ManaReaver",
            "name": "Mana-Reaver",
            "desc": "",
            "imageUrl": "//cdn.lolchess.gg/images/tft/traiticons-darken/trait_icon_manareaver.png",
            "blackImageUrl": "//cdn.lolchess.gg/images/tft/traiticons-black/trait_icon_manareaver.png",
            "whiteImageUrl": "//cdn.lolchess.gg/images/tft/traiticons-white/trait_icon_manareaver.png",
            "type": "CLASS",
            "styles": [
                {
                    "style": "gold",
                    "min": 2
                }
            ],
            "stats": {
                "2": "Mana-Reaver attacks increase the mana cost of their target’s next spell by 30%"
            }
        },
        {
            "key": "MechPilot",
            "ingameKey": "MechPilot",
            "name": "Mech-Pilot",
            "desc": "The Super-Mech has the traits of its pilots, 3random items from among them and gains 65% of the combined pilot's health and attack damage When the Super-Mech dies the Piots are ejected with 35% of thier maximun health and continue of fight",
            "imageUrl": "//cdn.lolchess.gg/images/tft/traiticons-darken/trait_icon_mechpilot.png",
            "blackImageUrl": "//cdn.lolchess.gg/images/tft/traiticons-black/trait_icon_mechpilot.png",
            "whiteImageUrl": "//cdn.lolchess.gg/images/tft/traiticons-white/trait_icon_mechpilot.png",
            "type": "ORIGIN",
            "styles": [
                {
                    "style": "gold",
                    "min": 3
                }
            ],
            "stats": {
                "3": "At the start of combat, three random mech-pilots are teleported into a super-mech"
            }
        },
        {
            "key": "Mercenary",
            "ingameKey": "Mercenary",
            "name": "Mercenary",
            "desc": "",
            "imageUrl": "//cdn.lolchess.gg/images/tft/traiticons-darken/trait_icon_mercenary.png",
            "blackImageUrl": "//cdn.lolchess.gg/images/tft/traiticons-black/trait_icon_mercenary.png",
            "whiteImageUrl": "//cdn.lolchess.gg/images/tft/traiticons-white/trait_icon_mercenary.png",
            "type": "CLASS",
            "styles": [
                {
                    "style": "gold",
                    "min": 1
                }
            ],
            "stats": {
                "1": "Innate: Upgrades for Mercenaries's spells have a chance to appear in the shop."
            }
        },
        {
            "key": "Mystic",
            "ingameKey": "Set3_Mystic",
            "name": "Mystic",
            "desc": "All allies gain Magic Resistance.",
            "imageUrl": "//cdn.lolchess.gg/images/tft/traiticons-darken/trait_icon_mystic.png",
            "blackImageUrl": "//cdn.lolchess.gg/images/tft/traiticons-black/trait_icon_mystic.png",
            "whiteImageUrl": "//cdn.lolchess.gg/images/tft/traiticons-white/trait_icon_mystic.png",
            "type": "CLASS",
            "styles": [
                {
                    "style": "bronze",
                    "min": 2,
                    "max": 3
                },
                {
                    "style": "gold",
                    "min": 4
                }
            ],
            "stats": {
                "2": "50 Magic Resistance",
                "4": "120 Magic Resistance"
            }
        },
        {
            "key": "Paragon",
            "ingameKey": "Paragon",
            "name": "Paragon",
            "desc": "",
            "imageUrl": "//cdn.lolchess.gg/images/tft/traiticons-darken/trait_icon_paragon.png",
            "blackImageUrl": "//cdn.lolchess.gg/images/tft/traiticons-black/trait_icon_paragon.png",
            "whiteImageUrl": "//cdn.lolchess.gg/images/tft/traiticons-white/trait_icon_paragon.png",
            "type": "CLASS",
            "styles": [
                {
                    "style": "gold",
                    "min": 1
                }
            ],
            "stats": {
                "1": "Ally Star Guardian basic attacks are converted to true damage. All other ally basic attacks are converted to magic damage."
            }
        },
        {
            "key": "Protector",
            "ingameKey": "Protector",
            "name": "Protector",
            "desc": "Protectors shield themselves for 4 seconds whenever they cast a spell. This shield doesn't stack.",
            "imageUrl": "//cdn.lolchess.gg/images/tft/traiticons-darken/trait_icon_protector.png",
            "blackImageUrl": "//cdn.lolchess.gg/images/tft/traiticons-black/trait_icon_protector.png",
            "whiteImageUrl": "//cdn.lolchess.gg/images/tft/traiticons-white/trait_icon_protector.png",
            "type": "CLASS",
            "styles": [
                {
                    "style": "bronze",
                    "min": 2,
                    "max": 3
                },
                {
                    "style": "silver",
                    "min": 4,
                    "max": 5
                },
                {
                    "style": "gold",
                    "min": 6
                }
            ],
            "stats": {
                "2": "30% Maximum Health Shield",
                "4": "40% Maximum Health Shield",
                "6": "50% Maximum Health Shield"
            }
        },
        {
            "key": "Rebel",
            "ingameKey": "Rebel",
            "name": "Rebel",
            "desc": "At the start of combat, Rebels gain a shield and increased damage for each adjacent Rebel. The shield lasts for 8 seconds.",
            "imageUrl": "//cdn.lolchess.gg/images/tft/traiticons-darken/trait_icon_rebel.png",
            "blackImageUrl": "//cdn.lolchess.gg/images/tft/traiticons-black/trait_icon_rebel.png",
            "whiteImageUrl": "//cdn.lolchess.gg/images/tft/traiticons-white/trait_icon_rebel.png",
            "type": "ORIGIN",
            "styles": [
                {
                    "style": "bronze",
                    "min": 3,
                    "max": 5
                },
                {
                    "style": "silver",
                    "min": 6,
                    "max": 8
                },
                {
                    "style": "gold",
                    "min": 9
                }
            ],
            "stats": {
                "3": "150 Shield & 10% Damage",
                "6": "225 Shield & 12% Damage",
                "9": "400 Shield & 20% Damage"
            }
        },
        {
            "key": "Sniper",
            "ingameKey": "Sniper",
            "name": "Sniper",
            "desc": "Snipers deal increased damage for each hex between themselves and their target.",
            "imageUrl": "//cdn.lolchess.gg/images/tft/traiticons-darken/trait_icon_sniper.png",
            "blackImageUrl": "//cdn.lolchess.gg/images/tft/traiticons-black/trait_icon_sniper.png",
            "whiteImageUrl": "//cdn.lolchess.gg/images/tft/traiticons-white/trait_icon_sniper.png",
            "type": "CLASS",
            "styles": [
                {
                    "style": "bronze",
                    "min": 2,
                    "max": 3
                },
                {
                    "style": "gold",
                    "min": 4
                }
            ],
            "stats": {
                "2": "9% increased damage for each hex",
                "4": "16% increased damage for each hex"
            }
        },
        {
            "key": "Sorcerer",
            "ingameKey": "Set3_Sorcerer",
            "name": "Sorcerer",
            "desc": "All allies have increased Spell Power.",
            "imageUrl": "//cdn.lolchess.gg/images/tft/traiticons-darken/trait_icon_sorcerer.png",
            "blackImageUrl": "//cdn.lolchess.gg/images/tft/traiticons-black/trait_icon_sorcerer.png",
            "whiteImageUrl": "//cdn.lolchess.gg/images/tft/traiticons-white/trait_icon_sorcerer.png",
            "type": "CLASS",
            "styles": [
                {
                    "style": "bronze",
                    "min": 2,
                    "max": 3
                },
                {
                    "style": "silver",
                    "min": 4,
                    "max": 5
                },
                {
                    "style": "gold",
                    "min": 6
                }
            ],
            "stats": {
                "2": "20% Spell Power",
                "4": "40% Spell Power",
                "6": "70% Spell Power"
            }
        },
        {
            "key": "SpacePirate",
            "ingameKey": "SpacePirate",
            "name": "Space Pirate",
            "desc": "Whenever a Space Pirate lands a killing blow on a Champion there is a chance to drop extra loot.",
            "imageUrl": "//cdn.lolchess.gg/images/tft/traiticons-darken/trait_icon_spacepirate.png",
            "blackImageUrl": "//cdn.lolchess.gg/images/tft/traiticons-black/trait_icon_spacepirate.png",
            "whiteImageUrl": "//cdn.lolchess.gg/images/tft/traiticons-white/trait_icon_spacepirate.png",
            "type": "ORIGIN",
            "styles": [
                {
                    "style": "bronze",
                    "min": 2,
                    "max": 3
                },
                {
                    "style": "gold",
                    "min": 4
                }
            ],
            "stats": {
                "2": "50% for 1 gold",
                "4": "50% for 1 gold and 33% for a component item"
            }
        },
        {
            "key": "StarGuardian",
            "ingameKey": "StarGuardian",
            "name": "Star Guardian",
            "desc": "Star Guardians' spellcasts grant Mana to other Star Guardians spread among them.",
            "imageUrl": "//cdn.lolchess.gg/images/tft/traiticons-darken/trait_icon_starguardian.png",
            "blackImageUrl": "//cdn.lolchess.gg/images/tft/traiticons-black/trait_icon_starguardian.png",
            "whiteImageUrl": "//cdn.lolchess.gg/images/tft/traiticons-white/trait_icon_starguardian.png",
            "type": "ORIGIN",
            "styles": [
                {
                    "style": "bronze",
                    "min": 3,
                    "max": 5
                },
                {
                    "style": "silver",
                    "min": 6,
                    "max": 8
                },
                {
                    "style": "gold",
                    "min": 9
                }
            ],
            "stats": {
                "3": "15 Total Mana",
                "6": "25 Total Mana",
                "9": "60 Total Mana"
            }
        },
        {
            "key": "Starship",
            "ingameKey": "Starship",
            "name": "Starship",
            "desc": "",
            "imageUrl": "//cdn.lolchess.gg/images/tft/traiticons-darken/trait_icon_starship.png",
            "blackImageUrl": "//cdn.lolchess.gg/images/tft/traiticons-black/trait_icon_starship.png",
            "whiteImageUrl": "//cdn.lolchess.gg/images/tft/traiticons-white/trait_icon_starship.png",
            "type": "CLASS",
            "styles": [
                {
                    "style": "gold",
                    "min": 1
                }
            ],
            "stats": {
                "1": "Innate: Starships gain 40 Mana per second, maneuver around the board, and are immune to movement impairing effects, but can't Basic Attack."
            }
        },
        {
            "key": "Valkyrie",
            "ingameKey": "Valkyrie",
            "name": "Valkyrie",
            "desc": "",
            "imageUrl": "//cdn.lolchess.gg/images/tft/traiticons-darken/trait_icon_valkyrie.png",
            "blackImageUrl": "//cdn.lolchess.gg/images/tft/traiticons-black/trait_icon_valkyrie.png",
            "whiteImageUrl": "//cdn.lolchess.gg/images/tft/traiticons-white/trait_icon_valkyrie.png",
            "type": "ORIGIN",
            "styles": [],
            "stats": {
                "2": "Valkyrie attacks and spells always critically hit targets below 40% health."
            },
            "isHidden": true
        },
        {
            "key": "Vanguard",
            "ingameKey": "Vanguard",
            "name": "Vanguard",
            "desc": "Vanguard champions gain bonus Armor.",
            "imageUrl": "//cdn.lolchess.gg/images/tft/traiticons-darken/trait_icon_vanguard.png",
            "blackImageUrl": "//cdn.lolchess.gg/images/tft/traiticons-black/trait_icon_vanguard.png",
            "whiteImageUrl": "//cdn.lolchess.gg/images/tft/traiticons-white/trait_icon_vanguard.png",
            "type": "CLASS",
            "styles": [
                {
                    "style": "bronze",
                    "min": 2,
                    "max": 3
                },
                {
                    "style": "silver",
                    "min": 4,
                    "max": 5
                },
                {
                    "style": "gold",
                    "min": 6
                }
            ],
            "stats": {
                "2": "125 Armor",
                "4": "300 Armor",
                "6": "900 Armor"
            }
        },
        {
            "key": "Void",
            "ingameKey": "Set3_Void",
            "name": "Void",
            "desc": "",
            "imageUrl": "//cdn.lolchess.gg/images/tft/traiticons-darken/trait_icon_void.png",
            "blackImageUrl": "//cdn.lolchess.gg/images/tft/traiticons-black/trait_icon_void.png",
            "whiteImageUrl": "//cdn.lolchess.gg/images/tft/traiticons-white/trait_icon_void.png",
            "type": "ORIGIN",
            "styles": [],
            "stats": {
                "3": "Attacks and spells from Void champions deal true damage."
            },
            "isHidden": true
        }
    ]
}