{
    "season": "set5",
    "items": [
        {
            "key": "BFSword",
            "ingameKey": "TFT_Item_BFSword",
            "name": "B.F. Sword",
            "desc": "+10 Attack Damage",
            "shortDesc": "+10 AD",
            "fromDesc": "",
            "imageUrl": "//ddragon.leagueoflegends.com/cdn/13.5.1/img/tft-item/TFT_Item_BFSword.png",
            "isFromItem": true
        },
        {
            "key": "RecurveBow",
            "ingameKey": "TFT_Item_RecurveBow",
            "name": "Recurve Bow",
            "desc": "+10% Attack Speed",
            "shortDesc": "+10% AS",
            "fromDesc": "",
            "imageUrl": "//ddragon.leagueoflegends.com/cdn/13.5.1/img/tft-item/TFT_Item_RecurveBow.png",
            "isFromItem": true
        },
        {
            "key": "NeedlesslyLargeRod",
            "ingameKey": "TFT_Item_NeedlesslyLargeRod",
            "name": "Needlessly Large Rod",
            "desc": "+10 Ability Power",
            "shortDesc": "+10% AP",
            "fromDesc": "",
            "imageUrl": "//ddragon.leagueoflegends.com/cdn/13.5.1/img/tft-item/TFT_Item_NeedlesslyLargeRod.png",
            "isFromItem": true
        },
        {
            "key": "Tearofthegoddess",
            "ingameKey": "TFT_Item_TearOfTheGoddess",
            "name": "Tear of the Goddess",
            "desc": "+15 Mana",
            "shortDesc": "+15<br>Mana",
            "fromDesc": "",
            "imageUrl": "//ddragon.leagueoflegends.com/cdn/13.5.1/img/tft-item/TFT_Item_TearOfTheGoddess.png",
            "isFromItem": true
        },
        {
            "key": "ChainVest",
            "ingameKey": "TFT_Item_ChainVest",
            "name": "Chain Vest",
            "desc": "+20 Armor",
            "shortDesc": "+20 Armor",
            "fromDesc": "",
            "imageUrl": "//ddragon.leagueoflegends.com/cdn/13.5.1/img/tft-item/TFT_Item_ChainVest.png",
            "isFromItem": true
        },
        {
            "key": "NegatronCloak",
            "ingameKey": "TFT_Item_NegatronCloak",
            "name": "Negatron Cloak",
            "desc": "+20 Magic Resist",
            "shortDesc": "+20 MR",
            "fromDesc": "",
            "imageUrl": "//ddragon.leagueoflegends.com/cdn/13.5.1/img/tft-item/TFT_Item_NegatronCloak.png",
            "isFromItem": true
        },
        {
            "key": "GiantsBelt",
            "ingameKey": "TFT_Item_GiantsBelt",
            "name": "Giant's Belt",
            "desc": "+150 Health",
            "shortDesc": "+150 HP",
            "fromDesc": "",
            "imageUrl": "//ddragon.leagueoflegends.com/cdn/13.5.1/img/tft-item/TFT_Item_GiantsBelt.png",
            "isFromItem": true
        },
        {
            "key": "Spatula",
            "ingameKey": "TFT_Item_Spatula",
            "name": "Pfannenwender",
            "desc": "It must do something...",
            "shortDesc": "You will get<br>special ability",
            "fromDesc": "",
            "imageUrl": "//ddragon.leagueoflegends.com/cdn/13.5.1/img/tft-item/TFT_Item_Spatula.png",
            "isFromItem": true
        },
        {
            "key": "SparringGloves",
            "ingameKey": "TFT_Item_SparringGloves",
            "name": "Sparring Gloves",
            "desc": "+5% Critical Strike Chance<br>+10% Dodge Chance",
            "shortDesc": "+5%<br>Crit chance<br>+10%<br>Dodge Chance",
            "fromDesc": "",
            "imageUrl": "//ddragon.leagueoflegends.com/cdn/13.5.1/img/tft-item/TFT_Item_SparringGloves.png",
            "isFromItem": true
        },
        {
            "key": "LordsEdge",
            "ingameKey": "TFT_Item_Deathblade",
            "name": "Deathblade",
            "desc": "Contributing to a kill grants the holder +10 additional Attack Damage for the rest of combat.<br><br>This effect can stack any number of times (starting at 4).",
            "shortDesc": "On takedown<br>gain<br>+10 AD",
            "fromDesc": "+20 Attack Damage",
            "imageUrl": "//ddragon.leagueoflegends.com/cdn/13.5.1/img/tft-item/TFT_Item_Deathblade.png",
            "compositions": [
                "BFSword",
                "BFSword"
            ],
            "isNormal": true
        },
        {
            "key": "GiantSlayer",
            "ingameKey": "TFT_Item_MadredsBloodrazor",
            "name": "Giant Slayer",
            "desc": "The holder's Abilities and attacks do 10% bonus damage. If the target has more than 1650 maximum Health, the bonus increases to 75%.",
            "shortDesc": "Bonus dmg<br>depends on<br>enemy HP<br>",
            "fromDesc": "",
            "imageUrl": "//ddragon.leagueoflegends.com/cdn/13.5.1/img/tft-item/TFT_Item_MadredsBloodrazor.png",
            "compositions": [
                "BFSword",
                "RecurveBow"
            ],
            "isNormal": true
        },
        {
            "key": "HextechGunblade",
            "ingameKey": "TFT_Item_HextechGunblade",
            "name": "Hextech Gunblade",
            "desc": "The holder's magic and true damage from Abilities heal them for 33% of the damage dealt. Excess healing fuels a shield that protects the holder against up to 300 damage.",
            "shortDesc": "Heal from<br>Ability dmg<br>Overhealing<br>fuels a shield",
            "fromDesc": "",
            "imageUrl": "//ddragon.leagueoflegends.com/cdn/13.5.1/img/tft-item/TFT_Item_HextechGunblade.png",
            "compositions": [
                "BFSword",
                "NeedlesslyLargeRod"
            ],
            "isNormal": true
        },
        {
            "key": "SpearofShojin",
            "ingameKey": "TFT_Item_SpearOfShojin",
            "name": "Spear of Shojin",
            "desc": "The wearer's Basic Attacks restore 8 additional Mana.",
            "shortDesc": "Restore<br>8 Mana<br>on-hit",
            "fromDesc": "",
            "imageUrl": "//ddragon.leagueoflegends.com/cdn/10.22.1/img/item/3161.png",
            "compositions": [
                "BFSword",
                "Tearofthegoddess"
            ],
            "isNormal": true
        },
        {
            "key": "GuardianAngel",
            "ingameKey": "TFT_Item_GuardianAngel",
            "name": "Guardian Angel",
            "desc": "Prevents the wearer's first death, placing them in stasis instead. After 2 seconds, they return with 400 Health and shed all negative effects.<br><br>[Unique - Only One Per Champion]",
            "shortDesc": "Revive with<br>400 HP<br>after<br>2 secs.",
            "fromDesc": "",
            "imageUrl": "//cdn.lolchess.gg/upload/images/items/3026_e7HQ3Dk8uK5ifoaQhflh2nfSkzYG5gthIizoaiPZ.png",
            "compositions": [
                "BFSword",
                "ChainVest"
            ],
            "isUnique": true,
            "isNormal": true
        },
        {
            "key": "Bloodthirster",
            "ingameKey": "TFT_Item_Bloodthirster",
            "name": "Bloodthirster",
            "desc": "Basic attacks heal the wearer for 33% of the damage dealt.<br><br>Upon falling below 40% Health, the wearer gain a 30% max Health shield that lasts up to 5 seconds.",
            "shortDesc": "Basic Attack<br>dmg dealt 33%<br>heal and<br>gain shield",
            "fromDesc": "",
            "imageUrl": "//ddragon.leagueoflegends.com/cdn/13.5.1/img/tft-item/TFT_Item_Bloodthirster.png",
            "compositions": [
                "BFSword",
                "NegatronCloak"
            ],
            "isNormal": true
        },
        {
            "key": "ZekesHerald",
            "ingameKey": "TFT_Item_ZekesHerald",
            "name": "Zeke's Herald",
            "desc": "When combat begins, the wearer and all allies within 1 hexes in the same row gain +25% Attack Speed for the rest of combat.",
            "shortDesc": "+AS<br>wearer and<br>allies within<br>1 hex in<br>the same row",
            "fromDesc": "",
            "imageUrl": "//cdn.lolchess.gg/images/tft/item/ZekesHerald.png",
            "compositions": [
                "BFSword",
                "GiantsBelt"
            ],
            "isNormal": true
        },
        {
            "key": "SwordoftheDivine",
            "ingameKey": "TFT5_Item_SkirmisherSpatulaItem",
            "name": "Skirmisher Emblem",
            "desc": "The holder gains the Skirmisher trait.<br><br>[Unique - Only One Per Champion]",
            "shortDesc": "Holder gains<br>Skirmisher trait",
            "fromDesc": "",
            "imageUrl": "//cdn.lolchess.gg/upload/images/items/SwordoftheDivine_1654581884.png",
            "compositions": [
                "BFSword",
                "Spatula"
            ],
            "affectedTraitKey": "Skirmisher",
            "isUnique": true,
            "isEmblem": true
        },
        {
            "key": "InfinityEdge",
            "ingameKey": "TFT_Item_InfinityEdge",
            "name": "Infinity Edge",
            "desc": "Grants 75% Critical Strike Chance (including components). Each point of Critical Strike Chance above 100% becomes +1% Critical Strike Damage.<br><br>[Unique - Only One Per Champion]",
            "shortDesc": "+75% Crit.<br>(>100% Crit Chance become<br>+1% Crit Dmg)",
            "fromDesc": "+75% Crit Chance\r\n+10 Attack Damage",
            "imageUrl": "//ddragon.leagueoflegends.com/cdn/13.5.1/img/tft-item/TFT_Item_InfinityEdge.png",
            "compositions": [
                "BFSword",
                "SparringGloves"
            ],
            "isUnique": true,
            "isNormal": true
        },
        {
            "key": "RapidFirecannon",
            "ingameKey": "TFT_Item_RapidFireCannon",
            "name": "Rapid Firecannon",
            "desc": "Increases the wearer's Attack Range by 1 hex and grants 20% bonus Attack Speed.<br><br>The wearer's Basic Attacks can no longer miss.",
            "shortDesc": "+1 Attack<br>Range<br>Bonus +AS<br>No atk miss",
            "fromDesc": "+20% Attack Speed",
            "imageUrl": "//ddragon.leagueoflegends.com/cdn/13.5.1/img/tft-item/TFT_Item_RapidFireCannon.png",
            "compositions": [
                "RecurveBow",
                "RecurveBow"
            ],
            "isNormal": true
        },
        {
            "key": "GuinsoosRageblade",
            "ingameKey": "TFT_Item_GuinsoosRageblade",
            "name": "Guinsoo's Rageblade",
            "desc": "Attacks grant +6% bonus Attack Speed for the rest of combat.<br><br>This effect can stack any number of times.",
            "shortDesc": "+6% AS<br>Unlimitedly<br>Stackable",
            "fromDesc": "",
            "imageUrl": "//ddragon.leagueoflegends.com/cdn/13.5.1/img/tft-item/TFT_Item_GuinsoosRageblade.png",
            "compositions": [
                "RecurveBow",
                "NeedlesslyLargeRod"
            ],
            "isNormal": true
        },
        {
            "key": "StatikkShiv",
            "ingameKey": "TFT_Item_StatikkShiv",
            "name": "Statikk Shiv",
            "desc": "Every third Basic Attack from the wearer unleashes a chain lightning that bounces to 4 enemies, dealing 70 magic damage and reducing their Magic Resist by 50% for 5 seconds.",
            "shortDesc": "AP dmg<br>and MR shred<br>to 4 emenies<br>every 3rd atk",
            "fromDesc": "",
            "imageUrl": "//ddragon.leagueoflegends.com/cdn/13.5.1/img/tft-item/TFT_Item_StatikkShiv.png",
            "compositions": [
                "RecurveBow",
                "Tearofthegoddess"
            ],
            "isNormal": true
        },
        {
            "key": "TitansResolve",
            "ingameKey": "TFT_Item_TitansResolve",
            "name": "Titan’s Resolve",
            "desc": "When the wearer takes damage or inflicts a critical hit, they gain 3 Attack Damage and Spell Power.<br><br>This stacks up to 25 times, at which point the wearer gains 25 Armor and Magic Resist.",
            "shortDesc": "Stack AD&AP<br>when taken<br>dmg or crit hit.<br>At max stacks<br>gain +AR&MR",
            "fromDesc": "",
            "imageUrl": "//ddragon.leagueoflegends.com/cdn/13.5.1/img/tft-item/TFT_Item_TitansResolve.png",
            "compositions": [
                "RecurveBow",
                "ChainVest"
            ],
            "isNormal": true
        },
        {
            "key": "RunaansHurricane",
            "ingameKey": "TFT_Item_RunaansHurricane",
            "name": "Runaan's Hurricane",
            "desc": "Basic Attacks fire a bolt at another nearby enemy, dealing 75% of the wearer's Attack Damage and applying on-hit effects. These bolts can critical strike.",
            "shortDesc": "Attack<br>+1 enemies<br>(75% Dmg)",
            "fromDesc": "",
            "imageUrl": "//ddragon.leagueoflegends.com/cdn/13.5.1/img/tft-item/TFT_Item_RunaansHurricane.png",
            "compositions": [
                "RecurveBow",
                "NegatronCloak"
            ],
            "isNormal": true
        },
        {
            "key": "ZzRotPortal",
            "ingameKey": "TFT_Item_TitanicHydra",
            "name": "Zz'Rot Portal",
            "desc": "At the start of combat, the holder taunts enemies within 2 hexes.<br><br>When the holder dies, a Voidspawn arises taunting nearby enemies. Voidspawns that arise from summoned units are 25% effective.",
            "shortDesc": "Taunts enemies<br>Voidspawn<br>arises when<br>holder dies<br>It taunts again",
            "fromDesc": "",
            "imageUrl": "//ddragon.leagueoflegends.com/cdn/13.5.1/img/tft-item/TFT_Item_TitanicHydra.png",
            "compositions": [
                "RecurveBow",
                "GiantsBelt"
            ],
            "isNormal": true
        },
        {
            "key": "DuelistsZeal",
            "ingameKey": "TFT5_Item_LegionnaireSpatulaItem",
            "name": "Legionnaire Emblem",
            "desc": "The holder gains the Legionnaire trait.<br><br>[Unique - Only One Per Champion]",
            "shortDesc": "Holder gains<br>Legionnaire<br>trait",
            "fromDesc": "",
            "imageUrl": "//cdn.lolchess.gg/upload/images/items/DuelistsZeal_1654581963.png",
            "compositions": [
                "RecurveBow",
                "Spatula"
            ],
            "affectedTraitKey": "Legionnaire",
            "isUnique": true,
            "isEmblem": true
        },
        {
            "key": "LastWhisper",
            "ingameKey": "TFT_Item_LastWhisper",
            "name": "Last Whisper",
            "desc": "When the wearer inflicts a critical hit, the target's Armor is reduced by 70% for 5 seconds. This effect does not stack.<br><br>[Unique - Only One Per Champion]",
            "shortDesc": "Target's<br>armor<br>-70%<br>on crit.",
            "fromDesc": "+15% Crit Chance<br>+10% Attack Speed",
            "imageUrl": "//ddragon.leagueoflegends.com/cdn/13.5.1/img/tft-item/TFT_Item_LastWhisper.png",
            "compositions": [
                "RecurveBow",
                "SparringGloves"
            ],
            "isUnique": true,
            "isNormal": true
        },
        {
            "key": "RabadonsDeathcap",
            "ingameKey": "TFT_Item_RabadonsDeathcap",
            "name": "Rabadon's Deathcap",
            "desc": "Grants 70 bonus Ability Power (including components).",
            "shortDesc": "+70 AP",
            "fromDesc": "+20 Ability Power",
            "imageUrl": "//ddragon.leagueoflegends.com/cdn/13.5.1/img/tft-item/TFT_Item_RabadonsDeathcap.png",
            "compositions": [
                "NeedlesslyLargeRod",
                "NeedlesslyLargeRod"
            ],
            "isNormal": true
        },
        {
            "key": "LudensEcho",
            "ingameKey": "TFT_Item_ArchangelsStaff",
            "name": "Archangel's Staff",
            "desc": "Each time the holder casts their Ability, they gain Ability Power equal to 45% of their maximum Mana (this bonus applies to that Ability cast).",
            "shortDesc": "Casting spell<br>gain AP 45%<br>of holder's<br>max mana.",
            "fromDesc": "",
            "imageUrl": "//ddragon.leagueoflegends.com/cdn/13.5.1/img/tft-item/TFT_Item_ArchangelsStaff.png",
            "compositions": [
                "NeedlesslyLargeRod",
                "Tearofthegoddess"
            ],
            "isNormal": true
        },
        {
            "key": "LocketoftheIronSolari",
            "ingameKey": "TFT_Item_LocketOfTheIronSolari",
            "name": "Locket of the Iron Solari",
            "desc": "When combat begins, the wearer and all allies within 2 hexes in the same row gain a shield that blocks \r\n300/350/400 ★ damage for 8 seconds.",
            "shortDesc": "Gain shield<br>for 8s<br>adjacent allies<br>in 2 Hexes",
            "fromDesc": "",
            "imageUrl": "//ddragon.leagueoflegends.com/cdn/13.5.1/img/tft-item/TFT_Item_LocketOfTheIronSolari.png",
            "compositions": [
                "NeedlesslyLargeRod",
                "ChainVest"
            ],
            "isNormal": true
        },
        {
            "key": "IonicSpark",
            "ingameKey": "TFT_Item_IonicSpark",
            "name": "Ionic Spark",
            "desc": "Enemies within 2 hexes have their Magic Resist reduced by 50% (does not stack). When they cast a spell, they are zapped taking magic damage equal to 250% of their max Mana.",
            "shortDesc": "Reduce enemy<br>MR and taking<br>Magic dmg<br>within 2 Hex",
            "fromDesc": "",
            "imageUrl": "//cdn.lolchess.gg/images/tft/item/IonicSpark.png",
            "compositions": [
                "NeedlesslyLargeRod",
                "NegatronCloak"
            ],
            "isNormal": true
        },
        {
            "key": "Morellonomicon",
            "ingameKey": "TFT_Item_Morellonomicon",
            "name": "Morellonomicon",
            "desc": "When the holder deals magic damage with their Ability, they burn the target, dealing 25% of the target's maximum Health as true damage over 10 seconds, and reducing healing by 50% for the duration of the burn.<br><br>[Unique - Only One Per Champion]",
            "shortDesc": "Abilities burn<br>target dealing<br>dmg and<br>reduce healing",
            "fromDesc": "",
            "imageUrl": "//ddragon.leagueoflegends.com/cdn/13.5.1/img/tft-item/TFT_Item_Morellonomicon.png",
            "compositions": [
                "NeedlesslyLargeRod",
                "GiantsBelt"
            ],
            "isUnique": true,
            "isNormal": true
        },
        {
            "key": "MantleofDusk",
            "ingameKey": "TFT5_Item_SpellweaverSpatulaItem",
            "name": "Spellweaver Emblem",
            "desc": "The holder gains the Spellweaver trait.<br><br>[Unique - Only One Per Champion]",
            "shortDesc": "Holder gains<br>Spellweaver<br>trait",
            "fromDesc": "",
            "imageUrl": "//cdn.lolchess.gg/upload/images/items/MantleofDusk_1654581896.png",
            "compositions": [
                "NeedlesslyLargeRod",
                "Spatula"
            ],
            "affectedTraitKey": "Spellweaver",
            "isUnique": true,
            "isEmblem": true
        },
        {
            "key": "ArcaneGauntlet",
            "ingameKey": "TFT_Item_JeweledGauntlet",
            "name": "Jeweled Gauntlet",
            "desc": "The holder's magic and true damage from their Ability can critically strike. The holder gains +40% bonus critical strike damage.",
            "shortDesc": "Holder's ability<br>can crit and<br>deals bonus<br>critical dmg",
            "fromDesc": "+15% Crit Chance<br>+10 Ability Power",
            "imageUrl": "//ddragon.leagueoflegends.com/cdn/13.5.1/img/tft-item/TFT_Item_JeweledGauntlet.png",
            "compositions": [
                "NeedlesslyLargeRod",
                "SparringGloves"
            ],
            "isNormal": true
        },
        {
            "key": "BlueSentinel",
            "ingameKey": "TFT_Item_SeraphsEmbrace",
            "name": "Blue Buff",
            "desc": "After casting their Ability, the holder gains 20 mana.<br><br>[Unique - Only One Per Champion]",
            "shortDesc": "After casting<br>a ability<br>wearer's mana<br>is set to 20.",
            "fromDesc": "+30 Mana",
            "imageUrl": "//ddragon.leagueoflegends.com/cdn/13.5.1/img/tft-item/TFT_Item_SeraphsEmbrace.png",
            "compositions": [
                "Tearofthegoddess",
                "Tearofthegoddess"
            ],
            "isUnique": true,
            "isNormal": true
        },
        {
            "key": "FrozenHeart",
            "ingameKey": "TFT_Item_FrozenHeart",
            "name": "Frozen Heart",
            "desc": "Reduces the Attack Speed of enemies within 2 hexes by 25%.<br><br>[Unique - Only One Per Champion]",
            "shortDesc": "-25% AS<br>in 2 Hexes<br>Adjacent<br>Enemies",
            "fromDesc": "",
            "imageUrl": "//cdn.lolchess.gg/upload/images/items/3110_v0619r67zsjsowMlFniZvXGsVNfdNDwoYbeCcVFX.png",
            "compositions": [
                "Tearofthegoddess",
                "ChainVest"
            ],
            "isUnique": true,
            "isNormal": true
        },
        {
            "key": "Chalice",
            "ingameKey": "TFT_Item_Chalice",
            "name": "Chalice of Power",
            "desc": "When combat begins, the holder and all allies within 1 hex in the same row gain 25 Ability Power for the rest of combat.",
            "shortDesc": "+25 AP<br>for all allies<br>within 1 hex<br>in same row",
            "fromDesc": "",
            "imageUrl": "//ddragon.leagueoflegends.com/cdn/13.5.1/img/tft-item/TFT_Item_Chalice.png",
            "compositions": [
                "Tearofthegoddess",
                "NegatronCloak"
            ],
            "isNormal": true
        },
        {
            "key": "Redemption",
            "ingameKey": "TFT_Item_Redemption",
            "name": "Redemption",
            "desc": "Every 5 seconds, the holder radiates an aura to allies within 1 Hex, healing them for 20% of their missing Health.<br><br>Affected allies take 25% reduced damage from area-of-effect attacks for 5 seconds",
            "shortDesc": "Heal allies<br>within 1 Hex &<br>Reduce<br>AoE dmg",
            "fromDesc": "",
            "imageUrl": "//ddragon.leagueoflegends.com/cdn/13.5.1/img/tft-item/TFT_Item_Redemption.png",
            "compositions": [
                "Tearofthegoddess",
                "GiantsBelt"
            ],
            "isNormal": true
        },
        {
            "key": "MagesCap",
            "ingameKey": "TFT5_Item_RenewerSpatulaItem",
            "name": "Renewer Emblem",
            "desc": "The holder gains the Renewer trait.<br><br>[Unique - Only One Per Champion]",
            "shortDesc": "Holder gains<br>Renewer trait",
            "fromDesc": "",
            "imageUrl": "//cdn.lolchess.gg/upload/images/items/MagesCap_1654581852.png",
            "compositions": [
                "Tearofthegoddess",
                "Spatula"
            ],
            "affectedTraitKey": "Renewer",
            "isUnique": true,
            "isEmblem": true
        },
        {
            "key": "HandofJustice",
            "ingameKey": "TFT_Item_UnstableConcoction",
            "name": "Hand of Justice",
            "desc": "At the begining of each planning phase, the wearer gains one of the following:<br>- +45 Attack Damage and +45 Ability Power.<br>- Attacks and Abilities heal for 40% of damage dealt.",
            "shortDesc": "+45% AD,<br>+45 AP or<br>40% heals<br>on hit",
            "fromDesc": "+15% Crit Chance<br>+15 Mana",
            "imageUrl": "//ddragon.leagueoflegends.com/cdn/13.5.1/img/tft-item/TFT_Item_UnstableConcoction.png",
            "compositions": [
                "Tearofthegoddess",
                "SparringGloves"
            ],
            "isNormal": true
        },
        {
            "key": "BrambleVest",
            "ingameKey": "TFT_Item_BrambleVest",
            "name": "Bramble Vest",
            "desc": "Negates bonus damage from incoming critical hits. On being hit by a Basic Attack, deal 80/100/150 ★ magic damage to all nearby enemies (once every 2.5 seconds).",
            "shortDesc": "Negate<br>bonus dmg<br>from crit. and<br>reflect dmg<br>to enemies",
            "fromDesc": "+40 Armor",
            "imageUrl": "//ddragon.leagueoflegends.com/cdn/13.5.1/img/tft-item/TFT_Item_BrambleVest.png",
            "compositions": [
                "ChainVest",
                "ChainVest"
            ],
            "isNormal": true
        },
        {
            "key": "IronWill",
            "ingameKey": "TFT_Item_GargoyleStoneplate",
            "name": "Gargoyle Stoneplate",
            "desc": "The holder gains 18 Armor and 18 Magic Resist for each enemy targeting them.",
            "shortDesc": "+18 AR &<br>+18 MR<br>for each<br>enemy<br>targeting them",
            "fromDesc": "",
            "imageUrl": "//ddragon.leagueoflegends.com/cdn/13.5.1/img/tft-item/TFT_Item_GargoyleStoneplate.png",
            "compositions": [
                "ChainVest",
                "NegatronCloak"
            ],
            "isNormal": true
        },
        {
            "key": "SunfireCape",
            "ingameKey": "TFT_Item_RedBuff",
            "name": "Sunfire Cape",
            "desc": "Every 2.5 seconds, a random enemy within 2 hexes is burned for 25% of their maximum health over 10 seconds. Any healing they receive is reduced by 50%.<br><br>[Unique - Only One Per Champion]",
            "shortDesc": "Burn an enemy<br>within 2 hexes<br>dealt dmg<br>reduce healing",
            "fromDesc": "",
            "imageUrl": "//ddragon.leagueoflegends.com/cdn/13.5.1/img/tft-item/TFT_Item_RedBuff.png",
            "compositions": [
                "ChainVest",
                "GiantsBelt"
            ],
            "isUnique": true,
            "isNormal": true
        },
        {
            "key": "VanguardsCuirass",
            "ingameKey": "TFT5_Item_IroncladSpatulaItem",
            "name": "Ironclad Emblem",
            "desc": "The holder gains the Ironclad trait.<br><br>[Unique - Only One Per Champion]",
            "shortDesc": "Holder gains<br>Ironclad trait",
            "fromDesc": "",
            "imageUrl": "//cdn.lolchess.gg/upload/images/items/VanguardsCuirass_1654581798.png",
            "compositions": [
                "ChainVest",
                "Spatula"
            ],
            "affectedTraitKey": "Ironclad",
            "isUnique": true,
            "isEmblem": true
        },
        {
            "key": "Shroud",
            "ingameKey": "TFT_Item_Shroud",
            "name": "Shroud of Stillness",
            "desc": "When combat begins, the wearer shoots a beam straight ahead that delays affected enemies' first spellcast, increasing their max Mana by 35% until they cast.<br><br>[Unique - Only One Per Champion]",
            "shortDesc": "Beamed<br>enemies<br>Max MP<br>+35%",
            "fromDesc": "+15% Dodge Chance<br>+20 Armor",
            "imageUrl": "//ddragon.leagueoflegends.com/cdn/13.5.1/img/tft-item/TFT_Item_Shroud.png",
            "compositions": [
                "ChainVest",
                "SparringGloves"
            ],
            "isUnique": true,
            "isNormal": true
        },
        {
            "key": "DragonsClaw",
            "ingameKey": "TFT_Item_DragonsClaw",
            "name": "Dragon's Claw",
            "desc": "Grants 250 bonus Magic Resist (including components).",
            "shortDesc": "+250<br>MR",
            "fromDesc": "+40 Magic Resist",
            "imageUrl": "//ddragon.leagueoflegends.com/cdn/13.5.1/img/tft-item/TFT_Item_DragonsClaw.png",
            "compositions": [
                "NegatronCloak",
                "NegatronCloak"
            ],
            "isNormal": true
        },
        {
            "key": "Zephyr",
            "ingameKey": "TFT_Item_Zephyr",
            "name": "Zephyr",
            "desc": "When combat begins, the wearer summons a whirlwind on the opposite side of the arena that removes the closest enemy from combat for 5 seconds. Ignores CC immunity.<br><br>[Unique - Only One Per Champion]",
            "shortDesc": "Banish<br>an enemy<br>for 5 secs",
            "fromDesc": "",
            "imageUrl": "//ddragon.leagueoflegends.com/cdn/13.5.1/img/tft-item/TFT_Item_Zephyr.png",
            "compositions": [
                "NegatronCloak",
                "GiantsBelt"
            ],
            "isUnique": true,
            "isNormal": true
        },
        {
            "key": "ElderwoodHeirloom",
            "ingameKey": "TFT5_Item_RedeemedSpatulaItem",
            "name": "Redeemed Emblem",
            "desc": "The holder gains the Redeemed trait.<br><br>[Unique - Only One Per Champion]",
            "shortDesc": "Holder gains<br>Redeemed trait",
            "fromDesc": "",
            "imageUrl": "//cdn.lolchess.gg/upload/images/items/ElderwoodHeirloom_1654581835.png",
            "compositions": [
                "NegatronCloak",
                "Spatula"
            ],
            "affectedTraitKey": "Redeemed",
            "isUnique": true,
            "isEmblem": true
        },
        {
            "key": "Quicksilver",
            "ingameKey": "TFT_Item_Quicksilver",
            "name": "Quicksilver",
            "desc": "The wearer is immune to crowd control for the first 12 seconds of combat.<br><br>[Unique - Only One Per Champion]",
            "shortDesc": "Immune to CC<br>for first 12s",
            "fromDesc": "+15% Dodge Chance<br>+20 Magic Resist",
            "imageUrl": "//ddragon.leagueoflegends.com/cdn/13.5.1/img/tft-item/TFT_Item_Quicksilver.png",
            "compositions": [
                "NegatronCloak",
                "SparringGloves"
            ],
            "isUnique": true,
            "isNormal": true
        },
        {
            "key": "WarmogsArmor",
            "ingameKey": "TFT_Item_WarmogsArmor",
            "name": "Warmog's Armor",
            "desc": "Grants 1000 bonus Health (including components).",
            "shortDesc": "+1000<br>HP",
            "fromDesc": "+300 Health",
            "imageUrl": "//ddragon.leagueoflegends.com/cdn/13.5.1/img/tft-item/TFT_Item_WarmogsArmor.png",
            "compositions": [
                "GiantsBelt",
                "GiantsBelt"
            ],
            "isNormal": true
        },
        {
            "key": "WarlordsBanner",
            "ingameKey": "TFT5_Item_DawnbringerSpatulaItem",
            "name": "Dawnbringer Emblem",
            "desc": "The holder gains the Dawnbringer trait.<br><br>[Unique - Only One Per Champion]",
            "shortDesc": "Holder gains<br>Dawnbringer<br>trait",
            "fromDesc": "",
            "imageUrl": "//cdn.lolchess.gg/upload/images/items/WarlordsBanner_1654581756.png",
            "compositions": [
                "GiantsBelt",
                "Spatula"
            ],
            "affectedTraitKey": "Dawnbringer",
            "isUnique": true,
            "isEmblem": true
        },
        {
            "key": "Backhand",
            "ingameKey": "TFT_Item_PowerGauntlet",
            "name": "Trap Claw",
            "desc": "Blocks the first enemy Ability that hits the holder, and stuns the Ability's caster for 4 seconds.<br><br>[Unique - Only One Per Champion]",
            "shortDesc": "Block a spell<br>and stun<br>the caster<br>for 4secs.",
            "fromDesc": "+15% Dodge Chance<br>+150 Health",
            "imageUrl": "//cdn.lolchess.gg/images/tft/item/Backhand.png",
            "compositions": [
                "GiantsBelt",
                "SparringGloves"
            ],
            "isUnique": true,
            "isNormal": true
        },
        {
            "key": "ForceofNature",
            "ingameKey": "TFT_Item_ForceOfNature",
            "name": "Force of Nature",
            "desc": "Wearer's team gains +1 maximum team size.",
            "shortDesc": "+1<br>Team size",
            "fromDesc": "",
            "imageUrl": "//cdn.lolchess.gg/upload/images/items/ForceofNature_1654583064.png",
            "compositions": [
                "Spatula",
                "Spatula"
            ],
            "isNormal": true
        },
        {
            "key": "YoumuusGhostblade",
            "ingameKey": "TFT5_Item_AssassinSpatulaItem",
            "name": "Assassin Emblem",
            "desc": "The holder gains the Assassin trait.<br><br>[Unique - Only One Per Champion]",
            "shortDesc": "Holder gains<br>Assassin trait",
            "fromDesc": "+5% Crit chance<br>+10% Dodge chance",
            "imageUrl": "//cdn.lolchess.gg/upload/images/items/YoumuusGhostblade_1654581726.png",
            "compositions": [
                "Spatula",
                "SparringGloves"
            ],
            "affectedTraitKey": "Assassin",
            "isUnique": true,
            "isEmblem": true
        },
        {
            "key": "ThiefsGloves",
            "ingameKey": "TFT_Item_ThiefsGloves",
            "name": "Thief's Gloves",
            "desc": "At the beginning of each planning phase, the holder equip 2 temporary items. Temporary items increase in power based on your player level.<br><br>[Consumes Three item Slots. Cannot Grant Shadow Items]",
            "shortDesc": "Fetch two<br>temporary<br>non-Shadow<br>items",
            "fromDesc": "+15% Critical Strike Chance<br>+15% Dodge Chance",
            "imageUrl": "//ddragon.leagueoflegends.com/cdn/13.5.1/img/tft-item/TFT_Item_ThiefsGloves.png",
            "compositions": [
                "SparringGloves",
                "SparringGloves"
            ],
            "isUnique": true,
            "isNormal": true
        },
        {
            "key": "ShadowBFSword",
            "ingameKey": "TFT5_Item_BFSwordShadow",
            "name": "Shadow Sword",
            "desc": "+10 Attack Damage",
            "shortDesc": "+10 AD",
            "fromDesc": "",
            "imageUrl": "//cdn.lolchess.gg/upload/images/items/ShadowBFSword_1654582082.png",
            "isFromItem": true
        },
        {
            "key": "ShadowRecurveBow",
            "ingameKey": "TFT5_Item_RecurveBowShadow",
            "name": "Shadow Bow",
            "desc": "+10% Attack Speed",
            "shortDesc": "+10% AS",
            "fromDesc": "",
            "imageUrl": "//cdn.lolchess.gg/upload/images/items/ShadowRecurveBow_1654582204.png",
            "isFromItem": true
        },
        {
            "key": "ShadowNeedlesslyLargeRod",
            "ingameKey": "TFT5_Item_NeedlesslyLargeRodShadow",
            "name": "Shadow Rod",
            "desc": "+10 Ability Power",
            "shortDesc": "Ability Power +10",
            "fromDesc": "",
            "imageUrl": "//cdn.lolchess.gg/upload/images/items/ShadowNeedlesslyLargeRod_1654582312.png",
            "isFromItem": true
        },
        {
            "key": "ShadowTearofthegoddess",
            "ingameKey": "TFT5_Item_TearOfTheGoddessShadow",
            "name": "Shadow Tear",
            "desc": "+15 Mana",
            "shortDesc": "+15<br>Mana",
            "fromDesc": "",
            "imageUrl": "//cdn.lolchess.gg/upload/images/items/ShadowTearofthegoddess_1654582298.png",
            "isFromItem": true
        },
        {
            "key": "ShadowChainVest",
            "ingameKey": "TFT5_Item_ChainVestShadow",
            "name": "Shadow Vest",
            "desc": "+20 Armor",
            "shortDesc": "",
            "fromDesc": "",
            "imageUrl": "//cdn.lolchess.gg/upload/images/items/ShadowChainVest_1654582154.png",
            "isFromItem": true
        },
        {
            "key": "ShadowNegatronCloak",
            "ingameKey": "TFT5_Item_NegatronCloakShadow",
            "name": "Shadow Cloak",
            "desc": "+20 Magic Resist",
            "shortDesc": "+20 MR",
            "fromDesc": "",
            "imageUrl": "//cdn.lolchess.gg/upload/images/items/ShadowNegatronCloak_1654582325.png",
            "isFromItem": true
        },
        {
            "key": "ShadowGiantsBelt",
            "ingameKey": "TFT5_Item_GiantsBeltShadow",
            "name": "Shadow Belt",
            "desc": "+150 Health",
            "shortDesc": "+150 HP",
            "fromDesc": "",
            "imageUrl": "//cdn.lolchess.gg/upload/images/items/ShadowGiantsBelt_1654582168.png",
            "isFromItem": true
        },
        {
            "key": "ShadowSpatula",
            "ingameKey": "TFT5_Item_SpatulaShadow",
            "name": "Shadow Spatula",
            "desc": "It must do something evil...",
            "shortDesc": "You will get<br>special ability",
            "fromDesc": "",
            "imageUrl": "//cdn.lolchess.gg/upload/images/items/ShadowSpatula_1654582184.png",
            "isFromItem": true
        },
        {
            "key": "ShadowSparringGloves",
            "ingameKey": "TFT5_Item_SparringGlovesShadow",
            "name": "Shadow Gloves",
            "desc": "+5% Critical Strike Chance<br>+10% Dodge Chance",
            "shortDesc": "+5%<br>Crit chance<br>+10% Dodge chance",
            "fromDesc": "",
            "imageUrl": "//cdn.lolchess.gg/upload/images/items/ShadowSparringGloves_1654582360.png",
            "isFromItem": true
        },
        {
            "key": "CursedDeathblade",
            "ingameKey": "TFT5_Item_DeathbladeShadow",
            "name": "Caustic Deathblade",
            "desc": "Contributing to a kill grants the holder +15 Attack Damage for the rest of combat. This effect can stack any number of times (starting at 4). The holder receives -20% maximum Health.",
            "shortDesc": "+15 AD per<br>takedown<br>stackable (4~)<br>Wearer HP<br>reduced",
            "fromDesc": "+20 Attack Damage",
            "imageUrl": "//cdn.lolchess.gg/upload/images/items/CursedDeathblade_1654582526.png",
            "compositions": [
                "BFSword",
                "ShadowBFSword"
            ]
        },
        {
            "key": "EvilGiantSlayer",
            "ingameKey": "TFT5_Item_GiantSlayerShadow",
            "name": "Spectral Giantslayer",
            "desc": "The holder's Abilities and attacks do 50% bonus damage. If the target has more than 1100 maximum Health.",
            "shortDesc": "+50% dmg<br>to MaxHP<br>>1100 enemy",
            "fromDesc": "",
            "imageUrl": "//cdn.lolchess.gg/upload/images/items/EvilGiantSlayer_1654582693.png",
            "compositions": [
                "BFSword",
                "ShadowRecurveBow"
            ]
        },
        {
            "key": "CursedHextechGunblade",
            "ingameKey": "TFT5_Item_HextechGunbladeShadow",
            "name": "Hextech Gunblade Of Immortality",
            "desc": "The holder's magic and true damage from Abilities heals the ally with lowest percent Health for 60% of the damage dealt. This heal cannot affect the holder.",
            "shortDesc": "Heal the<br>low HP ally<br>Holder<br>can't be healed.",
            "fromDesc": "",
            "imageUrl": "//cdn.lolchess.gg/upload/images/items/CursedHextechGunblade_1654582593.png",
            "compositions": [
                "BFSword",
                "ShadowNeedlesslyLargeRod"
            ]
        },
        {
            "key": "CursedSpearofShojin",
            "ingameKey": "TFT5_Item_SpearOfShojinShadow",
            "name": "Spectral Spear of Shojin",
            "desc": "The wearer's attacks restore 14 additional Mana. The wearer deals 15% less damage.",
            "shortDesc": "Restore<br>14 Mana<br>on-hit.<br>Wearer deals<br>less dmg.",
            "fromDesc": "",
            "imageUrl": "//cdn.lolchess.gg/upload/images/items/CursedSpearofShojin_1654582429.png",
            "compositions": [
                "BFSword",
                "ShadowTearofthegoddess"
            ]
        },
        {
            "key": "GuardianFallenAngel",
            "ingameKey": "TFT5_Item_GuardianAngelShadow",
            "name": "Fallen Guardian Angel",
            "desc": "Prevents the holder's first death, placing them in stasis instead. After 2 seconds, they return with 70% Health and shed all negative effects. After this effect triggers, the holder's Attack Speed is reduced by 50% for the rest of combat.<br><br>[Unique - Only One Per Champion]",
            "shortDesc": "Revive with<br>70% HP<br>AS reduced",
            "fromDesc": "",
            "imageUrl": "//cdn.lolchess.gg/upload/images/items/GuardianFallenAngel_1654582759.png",
            "compositions": [
                "BFSword",
                "ShadowChainVest"
            ],
            "isUnique": true
        },
        {
            "key": "Riskthirster",
            "ingameKey": "TFT5_Item_BloodthirsterShadow",
            "name": "Riskthirster",
            "desc": "Physical damage heals the holder for 40% of the damage dealt. Each time the holder heals to 90% Health, they gain 30% Attack Speed for 4 seconds. The holder takes 25% of their maximum Health in true damage at the beginning of combat.",
            "shortDesc": "+40% lifesteal.<br>Holder takes dmg.<br>If healed up to 90%<br>gain AS (no stack)",
            "fromDesc": "",
            "imageUrl": "//cdn.lolchess.gg/upload/images/items/Riskthirster_1654582101.png",
            "compositions": [
                "BFSword",
                "ShadowNegatronCloak"
            ]
        },
        {
            "key": "ZekesEvilHerald",
            "ingameKey": "TFT5_Item_ZekesHeraldShadow",
            "name": "Zeke's Bleak Herald",
            "desc": "When combat begins, the holder reduces the Attack Speed of all allies within 1 hexes in the same row by -20%. The holder then gains +40% Attack Speed for each affected ally.",
            "shortDesc": "Wearer<br>+40% AS<br>adjacent<br>allies\r\nAS -20%",
            "fromDesc": "",
            "imageUrl": "//cdn.lolchess.gg/upload/images/items/ZekesEvilHerald_1654582738.png",
            "compositions": [
                "BFSword",
                "ShadowGiantsBelt"
            ]
        },
        {
            "key": "CursedInfinityEdge",
            "ingameKey": "TFT5_Item_InfinityEdgeShadow",
            "name": "Sacrificial Infinity Edge",
            "desc": "Grants +75% Critical Strike Chance (including components). Each point of Critical Strike Chance above 100% becomes +1% Critical Strike Damage. The holder also gains 30% Critical Strike Damage. Each time the holder attacks or cast their Ability, they take true damage equal to 3% of their maximum Health.<br><br>[Unique - Only One Per Champion]",
            "shortDesc": "+75% Crit.<br>(>100% Crit Chance become<br>+1% Crit Dmg)<br>+30% crit dmg.<br>feedback dmg.",
            "fromDesc": "+75% Crit Chance<br>+10 Attack Damage",
            "imageUrl": "//cdn.lolchess.gg/upload/images/items/CursedInfinityEdge_1654582495.png",
            "compositions": [
                "BFSword",
                "ShadowSparringGloves"
            ],
            "isUnique": true
        },
        {
            "key": "RapidDeathcannon",
            "ingameKey": "TFT5_Item_RapidFirecannonShadow",
            "name": "Rapid Deathcannon",
            "desc": "Increases the holder's Attack Range by 1 hex. Additionally, the holder gains +40% bonus Attack Speed when there are no enemies within 2 hex.<br><br>The holder's attacks can no longer miss.",
            "shortDesc": "+1 Range<br>+40% when <br>No adjacent<br>enemy",
            "fromDesc": "+20% Attack Speed",
            "imageUrl": "//cdn.lolchess.gg/upload/images/items/RapidDeathcannon_1654581997.png",
            "compositions": [
                "RecurveBow",
                "ShadowRecurveBow"
            ]
        },
        {
            "key": "GuinsoosEvilRageblade",
            "ingameKey": "TFT5_Item_GuinsoosRagebladeShadow",
            "name": "Guinsoo's Sacrificial Rageblade",
            "desc": "Attacks grant +9% bonus Attack Speed for the rest of combat. The bonus Attack Speed can stack any number of times. The holder is dealt 2.5% of their maximum Health as true damage each attack.",
            "shortDesc": "+9% AS<br>-2.5% HP(Stacked)",
            "fromDesc": "",
            "imageUrl": "//cdn.lolchess.gg/upload/images/items/GuinsoosEvilRageblade_1654582283.png",
            "compositions": [
                "RecurveBow",
                "ShadowNeedlesslyLargeRod"
            ]
        },
        {
            "key": "EvilStatikkShiv",
            "ingameKey": "TFT5_Item_StatikkShivShadow",
            "name": "Statikk Stiletto",
            "desc": "Every other attack from the holder unleashes chain lightning that strikes 4 enemies, dealing 70 magic damage and reducing their Magic Resist by 50% for 5 seconds.<br><br>The holder receives -33% Attack Damage.",
            "shortDesc": "AP Dmg &<br>-50% MR<br>to 4 enemies per atk<br>holder<br>-33% AD",
            "fromDesc": "",
            "imageUrl": "//cdn.lolchess.gg/upload/images/items/EvilStatikkShiv_1654582658.png",
            "compositions": [
                "RecurveBow",
                "ShadowTearofthegoddess"
            ]
        },
        {
            "key": "TitansExplosiveResolve",
            "ingameKey": "TFT5_Item_TitansResolveShadow",
            "name": "Titan's Revenge",
            "desc": "Every 3 seconds, the holder's next attack deals 20% of the total damage they have taken since the last empowered attack as true damage.",
            "shortDesc": "Taken dmg<br>empowers<br>next attack<br>per 3s",
            "fromDesc": "",
            "imageUrl": "//cdn.lolchess.gg/upload/images/items/TitansExplosiveResolve_1654582022.png",
            "compositions": [
                "RecurveBow",
                "ShadowChainVest"
            ]
        },
        {
            "key": "RunaansEvilHurricane",
            "ingameKey": "TFT5_Item_RunaansHurricaneShadow",
            "name": "Runaan's Untamed Hurricane",
            "desc": "The holder's attacks fire bolts at 2 nearby enemies, dealing 50% of the holder's Attack Damage. These bolts can critically strike but do not apply on-hit effects.",
            "shortDesc": "Attack<br>+2 enemies<br>(50% Dmg)<br>no on-hit",
            "fromDesc": "",
            "imageUrl": "//cdn.lolchess.gg/upload/images/items/RunaansEvilHurricane_1654582413.png",
            "compositions": [
                "RecurveBow",
                "ShadowNegatronCloak"
            ]
        },
        {
            "key": "ZzRotDarkPortal",
            "ingameKey": "TFT5_Item_ZzRotPortalShadow",
            "name": "Unstable Zz'Rot Portal",
            "desc": "At the start of combat, the holder taunts enemies within 2 hexes.<br><br>When the holder dies, an Unstable Voidspawn with 500 Health arises and taunts enemies again. When it dies it deals 500 true damage to enemies within 1 hex(es).<br><br>Voidspawns that arise from summoned units are 50% effective.",
            "shortDesc": "Construct arises<br>when holder<br>dies. It deals<br>true dmg<br>when it dies.",
            "fromDesc": "",
            "imageUrl": "//cdn.lolchess.gg/upload/images/items/ZzRotDarkPortal_1654582253.png",
            "compositions": [
                "RecurveBow",
                "ShadowGiantsBelt"
            ]
        },
        {
            "key": "FinalWhisper",
            "ingameKey": "TFT5_Item_LastWhisperShadow",
            "name": "Final Whisper",
            "desc": "When the holder inflicts a critical hit, the target's Armor and Magic Resist are reduced by 70% for 5 seconds. The holder's Armor and Magic Resist are also permanently reduced by 25%.",
            "shortDesc": "Target's<br>AR & MR<br>is shred on crit.<br>Wearer's AR & MR<br>shred also",
            "fromDesc": "+15% Crit Chance<br>+10% Attack Speed",
            "imageUrl": "//cdn.lolchess.gg/upload/images/items/FinalWhisper_1654583232.png",
            "compositions": [
                "RecurveBow",
                "ShadowSparringGloves"
            ]
        },
        {
            "key": "RabadonsCursedDeathcap",
            "ingameKey": "TFT5_Item_RabadonsDeathcapShadow",
            "name": "Rabadon's Caustic Deathcap",
            "desc": "Grants 100 bonus Ability Power (including components) and -20% maximum Health.",
            "shortDesc": "+100 SP<br>Max HP<br>Penalty",
            "fromDesc": "+20 Ability Power",
            "imageUrl": "//cdn.lolchess.gg/upload/images/items/RabadonsCursedDeathcap_1654582389.png",
            "compositions": [
                "NeedlesslyLargeRod",
                "ShadowNeedlesslyLargeRod"
            ]
        },
        {
            "key": "ArchdemonsStaff",
            "ingameKey": "TFT5_Item_LudensEchoShadow",
            "name": "Archdemon's Staff Of Immortality",
            "desc": "Each time the holder casts their Ability, they gain empty maximum Health equal to 350% of their maximum Mana. The holder then heals for that amount.",
            "shortDesc": "When casts spell<br>gain AP Proportion<br>to HP increase, Recover",
            "fromDesc": "",
            "imageUrl": "//cdn.lolchess.gg/upload/images/items/ArchdemonsStaff_1654582066.png",
            "compositions": [
                "NeedlesslyLargeRod",
                "ShadowTearofthegoddess"
            ]
        },
        {
            "key": "LocketoftheDarkSolari",
            "ingameKey": "TFT5_Item_LocketOfTheIronSolariShadow",
            "name": "Locket of the Silver Lunari",
            "desc": "When combat begins, the holder and all allies with 2 hexes in the same row gain 60 bonus Armor and Magic Resist, but gain 5 less Mana per attack.",
            "shortDesc": "Wearer &<br>adjacent allies<br>+AR&MR<br>mana -5",
            "fromDesc": "",
            "imageUrl": "//cdn.lolchess.gg/upload/images/items/LocketoftheDarkSolari_1654582811.png",
            "compositions": [
                "NeedlesslyLargeRod",
                "ShadowChainVest"
            ]
        },
        {
            "key": "IonicDarkSpark",
            "ingameKey": "TFT5_Item_IonicSparkShadow",
            "name": "Ionic Dark-Spark",
            "desc": "Enemies and allies (except the holder) within 2 hexes are zapped when they cast an ability, taking magic damage scaling with their maximum Mana. Enemies take 200% of their maximum Mana, and allies take 50% of their maximum Mana. Whenever an ally or enemy is zapped, the holder gains 10 Ability Power for the rest of combat.",
            "shortDesc": "All units<br>within 2 hexes<br>takes dmg<br>holder AP+10",
            "fromDesc": "",
            "imageUrl": "//cdn.lolchess.gg/upload/images/items/IonicDarkSpark_1654582675.png",
            "compositions": [
                "NeedlesslyLargeRod",
                "ShadowNegatronCloak"
            ]
        },
        {
            "key": "Morevillonomicon",
            "ingameKey": "TFT5_Item_MorellonomiconShadow",
            "name": "Mor-evil-lonomicon",
            "desc": "When the holder deals magic damage with their Ability, they burn the target, dealing 100% of the target's maximum Health as true damage over 25 seconds, and reducing healing by 50% for the duration of the burn.<br>The holder's Ability deals 50% less damage.<br><br>[Unique - Only One Per Champion]",
            "shortDesc": "Magic dmg -50%<br>spells burn<br>target dealing<br>100% Max HP<br>reducing healing",
            "fromDesc": "",
            "imageUrl": "//cdn.lolchess.gg/upload/images/items/Morevillonomicon_1654582342.png",
            "compositions": [
                "NeedlesslyLargeRod",
                "ShadowGiantsBelt"
            ],
            "isUnique": true
        },
        {
            "key": "PoisonedGauntlet",
            "ingameKey": "TFT5_Item_JeweledGauntletShadow",
            "name": "Sacrificial Gauntlet",
            "desc": "The holder gains 40% Critical Strike Damage and magic and true damage from their Ability can critically strike. The first time the holder casts their Ability each combat, they gain an additional 20% Critical Strike Chance for the remainder of combat (this bonus applies to that Ability cast). Each time the holder casts their Ability, they deal 100% of their maximum Mana to themselves as true damage.",
            "shortDesc": "Spells can<br>be crit<br>+crit dmg<br>lose<br>Max HP",
            "fromDesc": "+15% Crit Chance<br>+10 Ability Power",
            "imageUrl": "//cdn.lolchess.gg/upload/images/items/PoisonedGauntlet_1654583544.png",
            "compositions": [
                "NeedlesslyLargeRod",
                "ShadowSparringGloves"
            ]
        },
        {
            "key": "VeryDarkBlueBuff",
            "ingameKey": "TFT5_Item_BlueBuffShadow",
            "name": "Very Dark Blue Buff",
            "desc": "After casting their Ability, the holder gains 15 Mana. If the holder has less than 60% Health, this is increased to 50.<br><br>[Unique - Only One Per Champion]",
            "shortDesc": "After casting<br>a spell<br>Mana is set to<br>depends of<br>current HP",
            "fromDesc": "+30 Mana",
            "imageUrl": "//cdn.lolchess.gg/upload/images/items/VeryDarkBlueBuff_1654582123.png",
            "compositions": [
                "Tearofthegoddess",
                "ShadowTearofthegoddess"
            ],
            "isUnique": true
        },
        {
            "key": "FrozenDarkHeart",
            "ingameKey": "TFT5_Item_FrozenHeartShadow",
            "name": "Frozen Dark Heart",
            "desc": "Reduces the Attack Speed of all enemies within 2 hexes by 35%.<br><br>The Attack Speed of allies (except the wearer) within 1 hex is reduced by 35%.<br><br>[Unique - Only One Per Champion]",
            "shortDesc": "Slow 35% AS<br>enemies in<br>2 Hex<br>and allies<br>in 1 Hex.",
            "fromDesc": "",
            "imageUrl": "//cdn.lolchess.gg/upload/images/items/FrozenDarkHeart_1654582794.png",
            "compositions": [
                "Tearofthegoddess",
                "ShadowChainVest"
            ],
            "isUnique": true
        },
        {
            "key": "ChaliceofMalice",
            "ingameKey": "TFT5_Item_ChaliceOfPowerShadow",
            "name": "Chalice of Malice",
            "desc": "When combat begins, all of the holder's allies within 1 hex in the same row gain 40 Ability Power for the rest of combat. The holder loses 20 Ability Power instead of gaining any.",
            "shortDesc": "+40 SP<br>for all allies<br>within 1 hex<br>in same row<br>wearer's SP -20",
            "fromDesc": "",
            "imageUrl": "//cdn.lolchess.gg/upload/images/items/ChaliceofMalice_1654582626.png",
            "compositions": [
                "Tearofthegoddess",
                "ShadowNegatronCloak"
            ]
        },
        {
            "key": "LackofRedemption",
            "ingameKey": "TFT5_Item_RedemptionShadow",
            "name": "Sacrificial Redemption",
            "desc": "The holder radiates an aura to all allies on the board except themself, and heals them for 25% of their missing Health every 5 seconds. Each time this happens, the holder damages themselves for 5% of their current Health as true damage.",
            "shortDesc": "Heal all allies<br>wearer takes<br>5% current HP",
            "fromDesc": "",
            "imageUrl": "//cdn.lolchess.gg/upload/images/items/LackofRedemption_1654582865.png",
            "compositions": [
                "Tearofthegoddess",
                "ShadowGiantsBelt"
            ]
        },
        {
            "key": "HandofVengence",
            "ingameKey": "TFT5_Item_HandOfJusticeShadow",
            "name": "Hand of Vengeance",
            "desc": "At the beginning of combat, the holder gains both of the following:<br>- +40 Attack Damage and +40 Ability Power.<br>- Attacks and Abilities heal for 40% of damage dealt.<br>These bonuses expire after each takedown, and renew on the next.",
            "shortDesc": "+40 AD<br>+40 AP<br>and 40%<br>heals on hit<br>takedowns<br>toggle buff.",
            "fromDesc": "+15% Crit Chance<br>+15 Mana",
            "imageUrl": "//cdn.lolchess.gg/upload/images/items/HandofVengence_1654582558.png",
            "compositions": [
                "Tearofthegoddess",
                "ShadowSparringGloves"
            ]
        },
        {
            "key": "VillainsBrambleVest",
            "ingameKey": "TFT5_Item_BrambleVestShadow",
            "name": "Refracted Bramble Vest",
            "desc": "Grants 200 bonus Armor (including components).",
            "shortDesc": "+200 AR",
            "fromDesc": "+40 Armor",
            "imageUrl": "//cdn.lolchess.gg/upload/images/items/VillainsBrambleVest_1654582137.png",
            "compositions": [
                "ChainVest",
                "ShadowChainVest"
            ]
        },
        {
            "key": "EvilGargoyleStoneplate",
            "ingameKey": "TFT5_Item_GargoyleStoneplateShadow",
            "name": "Gargoyle Stoneplate Of Immortality",
            "desc": "The holder heals themself for 45 health every 2 seconds for each unit targeting them.",
            "shortDesc": "Heals HP<br>for each enemy<br>targeting them",
            "fromDesc": "",
            "imageUrl": "//cdn.lolchess.gg/upload/images/items/EvilGargoyleStoneplate_1654582541.png",
            "compositions": [
                "ChainVest",
                "ShadowNegatronCloak"
            ]
        },
        {
            "key": "EclipseCape",
            "ingameKey": "TFT5_Item_SunfireCapeShadow",
            "name": "Eclipse Cape",
            "desc": "Every 1.5 second(s), a random enemy within 3 hexes is burned for 25% of their maximum Health as true damage over 10 seconds. Any healing they receive is reduced by 50%. The holder is also burned for 25% of their maximum Health as true damage over 8 seconds, and any healing they received is reduced by 50%.<br><br>[Unique - Only One Per Champion]",
            "shortDesc": "Burn an enemy<br>for 10 secs<br>within 3 hexes<br>dealt 25% of Max HP<br>Wearer also<br>be burned -25% HP for 8 sec",
            "fromDesc": "",
            "imageUrl": "//cdn.lolchess.gg/upload/images/items/EclipseCape_1654582847.png",
            "compositions": [
                "ChainVest",
                "ShadowGiantsBelt"
            ],
            "isUnique": true
        },
        {
            "key": "DarkShroudofStillness",
            "ingameKey": "TFT5_Item_ShroudOfStillnessShadow",
            "name": "Dark Shroud of Stillness",
            "desc": "When combat begins, the holder shoots a beam straight ahead and behind that delays affected enemies' and other allies' first ability cast, increasing their maximum Mana by 65% until they cast.<br><br>[Unique - Only One Per Champion]",
            "shortDesc": "Beamed<br>enemies<br>and allies<br>Max MP<br>+65%",
            "fromDesc": "+15% Dodge Chance<br>+20 Armor",
            "imageUrl": "//cdn.lolchess.gg/upload/images/items/DarkShroudofStillness_1654582905.png",
            "compositions": [
                "ChainVest",
                "ShadowSparringGloves"
            ],
            "isUnique": true
        },
        {
            "key": "DarkDragonsClaw",
            "ingameKey": "TFT5_Item_DragonsClawShadow",
            "name": "Refracted Dragon's Claw",
            "desc": "Reduces incoming magic damage by 15%. Negates bonus damage from incoming critical hits.",
            "shortDesc": "Magic dmb<br>15% reduce",
            "fromDesc": "+40 Magic Resist",
            "imageUrl": "//cdn.lolchess.gg/upload/images/items/DarkDragonsClaw_1654582270.png",
            "compositions": [
                "NegatronCloak",
                "ShadowNegatronCloak"
            ]
        },
        {
            "key": "ExplosiveZephyr",
            "ingameKey": "TFT5_Item_ZephyrShadow",
            "name": "Turbulent Zephyr",
            "desc": "When combat begins, the holder summons a whirlwind on the opposite side of the arena that removes the closest enemy from combat for 8 seconds. Once the enemy returns to combat, they gain 30 Attack Damage and Ability Power for the rest of combat. Ignores CC immunity.<br><br>[Unique - Only One Per Champion]",
            "shortDesc": "Banish<br>an enemy<br>for 8 secs<br>return with<br>+AP/AD",
            "fromDesc": "",
            "imageUrl": "//cdn.lolchess.gg/upload/images/items/ExplosiveZephyr_1654582479.png",
            "compositions": [
                "NegatronCloak",
                "ShadowGiantsBelt"
            ],
            "isUnique": true
        },
        {
            "key": "EvilQuicksilver",
            "ingameKey": "TFT5_Item_QuicksilverShadow",
            "name": "Caustic Quicksilver",
            "desc": "The wearer is immune to crowd control for the entirety of combat and receives -20% maximum Health.<br><br>[Unique - Only One Per Champion]",
            "shortDesc": "Immune to CC<br>Max HP -20%",
            "fromDesc": "+15% Dodge Chance<br>+20 Magic Resist",
            "imageUrl": "//cdn.lolchess.gg/upload/images/items/EvilQuicksilver_1654582574.png",
            "compositions": [
                "NegatronCloak",
                "ShadowSparringGloves"
            ],
            "isUnique": true
        },
        {
            "key": "WarmogsPoisonArmor",
            "ingameKey": "TFT5_Item_WarmogsArmorShadow",
            "name": "Warmog's Sacrificial Armor",
            "desc": "Grants 1800 bonus Health (including components). The holder takes 60 true damage each second.",
            "shortDesc": "HP<br>+1800.<br>-60 HP<br>per sec.",
            "fromDesc": "+300 Health",
            "imageUrl": "//cdn.lolchess.gg/upload/images/items/WarmogsPoisonArmor_1654582643.png",
            "compositions": [
                "GiantsBelt",
                "ShadowGiantsBelt"
            ]
        },
        {
            "key": "ExplosiveTrapClaw",
            "ingameKey": "TFT5_Item_TrapClawShadow ",
            "name": "Banshee’s Claw",
            "desc": "When combat begins, the holder and all allies within 1 hex(es) in the same row gain a shield that blocks the first enemy Ability.<br><br>[Unique - Only One Per Champion]",
            "shortDesc": "Wearer and adjacent<br>allies block a spell<br>once.",
            "fromDesc": "+15% Dodge Chance<br>+150 Health",
            "imageUrl": "//cdn.lolchess.gg/upload/images/items/ExplosiveTrapClaw_1654583146.png",
            "compositions": [
                "GiantsBelt",
                "ShadowSparringGloves"
            ],
            "isUnique": true
        },
        {
            "key": "ForceofDarkness",
            "ingameKey": "TFT5_Item_ForceOfNatureShadow",
            "name": "Force of Darkness",
            "desc": "The holder's team gains +2 maximum team size, but the player's Little Legend takes +100% damage after losing a battle.",
            "shortDesc": "+2 Team size<br>but<br>Little Legend<br>takes 2x dmg",
            "fromDesc": "　",
            "imageUrl": "//cdn.lolchess.gg/upload/images/items/ForceofDarkness_1654582720.png",
            "compositions": [
                "Spatula",
                "ShadowSpatula"
            ]
        },
        {
            "key": "CursedThiefsGlove",
            "ingameKey": "TFT5_Item_ThiefsGlovesShadow",
            "name": "Trickster's Gloves",
            "desc": "At the beginning of each planning phase, the holder equips 2 temporary items. These Items are always full shadow items.<br><br>[Consumes Three Item Slots]",
            "shortDesc": "Fetch two<br>temporary<br>full shadow<br>items",
            "fromDesc": "+15% Critical Strike Chance<br>+15% Dodge Chance",
            "imageUrl": "//cdn.lolchess.gg/upload/images/items/CursedThiefsGlove_1654582607.png",
            "compositions": [
                "SparringGloves",
                "ShadowSparringGloves"
            ],
            "isUnique": true
        },
        {
            "key": "ShadowSwordoftheDivine",
            "ingameKey": "TFT5_Item_ForgottenSpatulaItem",
            "name": "Forgotten Emblem",
            "desc": "The holder gains the Forgotten trait.<br><br>[Unique - Only One Per Champion]",
            "shortDesc": "Holder gains<br>Forgotten trait",
            "fromDesc": "+10 Attack Damage",
            "imageUrl": "//cdn.lolchess.gg/upload/images/items/ShadowSwordoftheDivine_1654581784.png",
            "compositions": [
                "BFSword",
                "ShadowSpatula"
            ],
            "affectedTraitKey": "Forgotten",
            "isUnique": true,
            "isEmblem": true
        },
        {
            "key": "ShadowDuelistsZeal",
            "ingameKey": "TFT5_Item_HellionSpatulaItem",
            "name": "Hellion Emblem",
            "desc": "The holder gains the Hellion trait.<br><br>[Unique - Only One Per Champion]",
            "shortDesc": "Holder gains<br>Hellion trait",
            "fromDesc": "+10% Attack Speed",
            "imageUrl": "//cdn.lolchess.gg/upload/images/items/ShadowDuelistsZeal_1654581662.png",
            "compositions": [
                "RecurveBow",
                "ShadowSpatula"
            ],
            "affectedTraitKey": "Hellion",
            "isUnique": true,
            "isEmblem": true
        },
        {
            "key": "ShadowMantleofDusk",
            "ingameKey": "TFT5_Item_DragonslayerSpatulaItem",
            "name": "Dragonslayer Emblem",
            "desc": "The holder gains the Dragonslayer trait.<br><br>[Unique - Only One Per Champion]",
            "shortDesc": "Holder gains<br>Dragonslayer trait",
            "fromDesc": "+10 Ability Power",
            "imageUrl": "//cdn.lolchess.gg/upload/images/items/ShadowMantleofDusk_1654581771.png",
            "compositions": [
                "NeedlesslyLargeRod",
                "ShadowSpatula"
            ],
            "affectedTraitKey": "Dragonslayer",
            "isUnique": true,
            "isEmblem": true
        },
        {
            "key": "ShadowMagesCap",
            "ingameKey": "TFT5_Item_CovenSpatulaItem",
            "name": "Coven Emblem",
            "desc": "The holder gains the Coven trait.<br><br>[Unique - Only One Per Champion]",
            "shortDesc": "Holder gains<br>Coven trait",
            "fromDesc": "+15 Mana",
            "imageUrl": "//cdn.lolchess.gg/upload/images/items/ShadowMagesCap_1654581684.png",
            "compositions": [
                "Tearofthegoddess",
                "ShadowSpatula"
            ],
            "affectedTraitKey": "Coven",
            "isUnique": true,
            "isEmblem": true
        },
        {
            "key": "ShadowVanguardsCuirass",
            "ingameKey": "TFT5_Item_CavalierSpatulaItem",
            "name": "Cavalier Emblem",
            "desc": "The holder gains the Cavalier trait.<br><br>[Unique - Only One Per Champion]",
            "shortDesc": "Holder gains<br>Cavalier trait",
            "fromDesc": "+20 Armor",
            "imageUrl": "//cdn.lolchess.gg/upload/images/items/ShadowVanguardsCuirass_1654581742.png",
            "compositions": [
                "ChainVest",
                "ShadowSpatula"
            ],
            "affectedTraitKey": "Cavalier",
            "isUnique": true,
            "isEmblem": true
        },
        {
            "key": "ShadowElderwoodHeirloom",
            "ingameKey": "TFT5_Item_RevenantSpatulaItem",
            "name": "Revenant Emblem",
            "desc": "The holder gains the Revenant trait.<br><br>[Unique - Only One Per Champion]",
            "shortDesc": "Holder gains<br>Revenant trait",
            "fromDesc": "+20 Magic Resist",
            "imageUrl": "//cdn.lolchess.gg/upload/images/items/ShadowElderwoodHeirloom_1654581867.png",
            "compositions": [
                "NegatronCloak",
                "ShadowSpatula"
            ],
            "affectedTraitKey": "Revenant",
            "isUnique": true,
            "isEmblem": true
        },
        {
            "key": "ShadowWarlordsBanner",
            "ingameKey": "TFT5_Item_NightbringerSpatulaItem",
            "name": "Nightbringer Emblem",
            "desc": "The holder gains the Nightbringer trait.<br><br>[Unique - Only One Per Champion]",
            "shortDesc": "Holder gains<br>Nightbringer trait",
            "fromDesc": "+150 Health",
            "imageUrl": "//cdn.lolchess.gg/upload/images/items/ShadowWarlordsBanner_1654581820.png",
            "compositions": [
                "GiantsBelt",
                "ShadowSpatula"
            ],
            "affectedTraitKey": "Nightbringer",
            "isUnique": true,
            "isEmblem": true
        },
        {
            "key": "ShadowYoumuusGhostblade",
            "ingameKey": "TFT5_Item_AbominationSpatulaItem",
            "name": "Abomination Emblem",
            "desc": "The holder gains the Abomination trait.<br><br>[Unique - Only One Per Champion]",
            "shortDesc": "Holder gains<br>Abomination trait",
            "fromDesc": "+5% Crit chance<br>+10% Dodge chance",
            "imageUrl": "//cdn.lolchess.gg/upload/images/items/ShadowYoumuusGhostblade_1654581705.png",
            "compositions": [
                "Spatula",
                "ShadowSparringGloves"
            ],
            "affectedTraitKey": "Abomination",
            "isUnique": true,
            "isEmblem": true
        }
    ]
}